jupyterlab_color_picker/__init__.py
jupyterlab_color_picker/_version.py
jupyterlab_color_picker-0.1.0.data/data/share/jupyter/labextensions/jupyterlab-color-picker/package.json
jupyterlab_color_picker-0.1.0.data/data/share/jupyter/labextensions/jupyterlab-color-picker/static/255.ed57596e47fb69367c6d.js
jupyterlab_color_picker-0.1.0.data/data/share/jupyter/labextensions/jupyterlab-color-picker/static/271.2e442c0392a3eae4301a.js
jupyterlab_color_picker-0.1.0.data/data/share/jupyter/labextensions/jupyterlab-color-picker/static/652.df44c038e5a86c301e50.js
jupyterlab_color_picker-0.1.0.data/data/share/jupyter/labextensions/jupyterlab-color-picker/static/728.08817c0706986b0dc3a8.js
jupyterlab_color_picker-0.1.0.data/data/share/jupyter/labextensions/jupyterlab-color-picker/static/remoteEntry.f56a712f79a665e443b1.js
jupyterlab_color_picker-0.1.0.data/data/share/jupyter/labextensions/jupyterlab-color-picker/static/style.js
jupyterlab_color_picker-0.1.0.data/data/share/jupyter/labextensions/jupyterlab-color-picker/static/third-party-licenses.json
jupyterlab_color_picker-0.1.0.data/data/share/jupyter/labextensions/jupyterlab-color-picker/install.json
jupyterlab_color_picker-0.1.0.dist-info/METADATA
jupyterlab_color_picker-0.1.0.dist-info/WHEEL
jupyterlab_color_picker-0.1.0.dist-info/licenses/LICENSE
jupyterlab_color_picker-0.1.0.dist-info/RECORD
