Metadata-Version: 2.3
Name: jupyterlab-color-picker
Version: 0.1.0
Dynamic: Keywords
Summary: A JupyterLab color picker
Project-URL: Homepage, https://github.com/krassowski/jupyterlab-color-picker
Project-URL: Bug Tracker, https://github.com/krassowski/jupyterlab-color-picker/issues
Project-URL: Repository, https://github.com/krassowski/jupyterlab-color-picker.git
Author: Michał Krassowski
License: BSD 3-Clause License
License-File: LICENSE
Classifier: Framework :: Jupyter
Classifier: Framework :: Jupyter :: JupyterLab
Classifier: Framework :: Jupyter :: JupyterLab :: 4
Classifier: Framework :: Jupyter :: JupyterLab :: Extensions
Classifier: Framework :: Jupyter :: JupyterLab :: Extensions :: Prebuilt
Classifier: License :: OSI Approved :: BSD License
Classifier: Programming Language :: Python
Classifier: Programming Language :: Python :: 3
Classifier: Programming Language :: Python :: 3.8
Classifier: Programming Language :: Python :: 3.9
Classifier: Programming Language :: Python :: 3.10
Classifier: Programming Language :: Python :: 3.11
Classifier: Programming Language :: Python :: 3.12
Requires-Python: >=3.8
